{
  "version": "7",
  "dialect": "postgresql",
  "entries": [
    {
      "idx": 0,
      "version": "7",
      "when": 1741274993603,
      "tag": "0000_init",
      "breakpoints": true
    },
    {
      "idx": 1,
      "version": "7",
      "when": 1741381619192,
      "tag": "0001_second",
      "breakpoints": true
    },
    {
      "idx": 2,
      "version": "7",
      "when": 1741472409868,
      "tag": "0002_third",
      "breakpoints": true
    },
    {
      "idx": 3,
      "version": "7",
      "when": 1741563305536,
      "tag": "0003_fourth",
      "breakpoints": true
    },
    {
      "idx": 4,
      "version": "7",
      "when": 1741565615891,
      "tag": "0004_fifth",
      "breakpoints": true
    }
  ]
}